risiko/__init__.py
risiko/core/__init__.py
risiko/core/exception.py
risiko/core/magazine/__init__.py
risiko/core/magazine/base.py
risiko/core/magazine/exception.py
risiko/core/magazine/interface.py
risiko/core/player/__init__.py
risiko/core/player/base.py
risiko/core/player/exception.py
risiko/core/player/interface.py
risiko/core/shell/__init__.py
risiko/core/shell/base.py
risiko/core/shell/exception.py
risiko/core/shell/interface.py
risiko/core/shotgun/__init__.py
risiko/core/shotgun/base.py
risiko/core/shotgun/exception.py
risiko/core/shotgun/interface.py
risiko/service/__init__.py
risiko/service/helper.py
risiko/service/risiko_state.py
risiko/service/managers/__init__.py
risiko/service/managers/player.py
risiko/service/managers/turn.py
risiko/service/processors/__init__.py
risiko/service/processors/action.py
risiko/service/processors/magazine.py
risiko/service/processors/player_management.py
risiko/service/processors/player_state.py
risiko/service/processors/turn.py
risiko/service/processors/weapon.py
risiko_engine-1.0.0.dist-info/licenses/LICENSE
risiko_engine-1.0.0.dist-info/METADATA
risiko_engine-1.0.0.dist-info/WHEEL
risiko_engine-1.0.0.dist-info/top_level.txt
risiko_engine-1.0.0.dist-info/RECORD
