Metadata-Version: 2.4
Name: risiko-engine
Version: 1.0.0
Summary: A Stateless Russian Roulette Python Engine
Author-email: Kodutzu <Kodutzu@gmail.com>
License-Expression: MIT
Project-URL: Repository, https://github.com/Kodutzu/risiko-engine
Project-URL: Bug Tracker, https://github.com/Kodutzu/risiko-engine/issues
Keywords: game,engine,roulette,stateless
Classifier: Programming Language :: Python :: 3.12
Classifier: Development Status :: 5 - Production/Stable
Classifier: Topic :: Games/Entertainment
Requires-Python: >=3.12
License-File: LICENSE
Requires-Dist: attrs
Provides-Extra: test
Requires-Dist: pytest; extra == "test"
Dynamic: license-file
